Workbook

Sheet Unit economics
A1: MetriQ unit economics (USD, per unit)
A2: Blue = input you can change. Black = formula. Yellow = key assumption to confirm.
A4: Item | B4: MetriQ Pro | C4: MetriQ Lite | D4: Note
A5: Edge computer + storage | B5: 2075 | C5: 589 | D5: Pro: Jetson AGX Orin 64GB $2,000 + 1TB NVMe $75. Lite: Minisforum UM790 Pro $589. Source: metriq-ai-box-bom.xlsx
A6: Camera, lighting, cable | B6: 584 | C6: 584 | D6: RealSense D435i $349, CCS LED bar $140, Newnex USB3 cable $95. Source: BOM
A7: Trigger sensor and reject I/O | B7: 230 | C7: 230 | D7: Omron E3Z-D62 $55, Advantech ADAM-6060 $175. Source: BOM
A8: Enclosure and mounting | B8: 300 | C8: 300 | D8: Source: BOM subtotal
A9: Power and networking | B9: 125 | C9: 125 | D9: Source: BOM subtotal
A10: Stack light, touchscreen, UPS | B10: 305 | C10: 305 | D10: Patlite tower $75, 7in HMI $150, UPS $80. Source: BOM optional add-ons
A11: Hardware total | B11: =SUM(B5:B10) -> 3619 | C11: =SUM(C5:C10) -> 2133 | D11: Single-unit prices, before shipping, duty and VAT (September 2026)
A13: Assumptions
A14: Shipping, duty, assembly (% of hardware) | B14: 0.2 | D14: Assumption - replace with real landed cost after first import
A15: Installation and travel per unit | B15: 800 | D15: Assumption - 1 engineer, 1-2 days on site incl. travel
A16: Proposed price - Pro | B16: 14000 | D16: Draft - owner to approve
A17: Proposed price - Lite | B17: 9000 | D17: Draft - owner to approve
A19: Result | B19: MetriQ Pro | C19: MetriQ Lite | D19: Note
A20: Hardware total | B20: =B11 -> 3619 | C20: =C11 -> 2133
A21: Shipping, duty, assembly | B21: =ROUND(B20*$B$14,0) -> 724 | C21: =ROUND(C20*$B$14,0) -> 427
A22: Installation and travel | B22: =$B$15 -> 800 | C22: =$B$15 -> 800
A23: Delivered cost | B23: =SUM(B20:B22) -> 5143 | C23: =SUM(C20:C22) -> 3360
A24: Proposed price | B24: =B16 -> 14000 | C24: =B17 -> 9000
A25: Gross profit | B25: =B24-B23 -> 8857 | C25: =C24-C23 -> 5640
A26: Gross margin (%) | B26: =IF(B24=0,0,ROUND(B25/B24*100,1)) -> 63.3 | C26: =IF(C24=0,0,ROUND(C25/C24*100,1)) -> 62.7
A28: Customer payback (Vietnam)
A29: Inspectors replaced per shift | B29: 2 | D29: Assumption - confirm in pilots
A30: Shifts per day | B30: 2
A31: Monthly wage per inspector | B31: 332 | D31: About VND 8.4M per month, Q1 2025. Source: Vietnam Briefing, Vietnam wages 2025
A32: Annual saving for customer | B32: =B29*B30*B31*12 -> 15936
A33: Payback - Pro (months) | B33: =IF(B32=0,0,ROUND(B24/B32*12,1)) -> 10.5
A34: Payback - Lite (months) | B34: =IF(B32=0,0,ROUND(C24/B32*12,1)) -> 6.8

Sheet Funding
A1: Funding request and use of funds (USD)
A3: Use of funds | B3: USD | C3: Share (%) | D3: Note
A4: Stock for 10 stations (hardware, landed) | B4: 43000 | C4: =IF($B$10=0,0,ROUND(B4/$B$10*100,1)) -> 35.8 | D4: Mix of Pro and Lite hardware incl. landed cost
A5: 2 demo stations (Vietnam, Canada) | B5: 12000 | C5: =IF($B$10=0,0,ROUND(B5/$B$10*100,1)) -> 10 | D5: Station + demo conveyor each
A6: Engineering: reject kit, reports, installer | B6: 30000 | C6: =IF($B$10=0,0,ROUND(B6/$B$10*100,1)) -> 25 | D6: Contract engineering, 12 months
A7: Sales and marketing: trade shows, demos, travel | B7: 12000 | C7: =IF($B$10=0,0,ROUND(B7/$B$10*100,1)) -> 10
A8: Electrical safety certification (CE / CSA) | B8: 8000 | C8: =IF($B$10=0,0,ROUND(B8/$B$10*100,1)) -> 6.7 | D8: Estimate - get quotes
A9: Contingency | B9: 15000 | C9: =IF($B$10=0,0,ROUND(B9/$B$10*100,1)) -> 12.5 | D9: 12.5% of total
A10: Total loan | B10: =SUM(B4:B9) -> 120000 | C10: =SUM(C4:C9) -> 100
A12: Loan terms
A13: Annual interest rate | B13: 0.1 | D13: Assumption - set by lender
A14: Term (years) | B14: 5
A15: Monthly payment | B15: =ROUND(PMT(B13/12,B14*12,-B10),0) -> 2550
A16: Annual payment | B16: =B15*12 -> 30600
A17: Pro units per year to cover payments | B17: =IF('Unit economics'!B25<=0,0,ROUNDUP(B16/'Unit economics'!B25,0)) -> 4
A19: Year-1 sales plan | B19: Units | C19: Revenue | D19: Gross profit
A20: MetriQ Pro | B20: 8 | C20: =B20*'Unit economics'!B24 -> 112000 | D20: =B20*'Unit economics'!B25 -> 70856
A21: MetriQ Lite | B21: 4 | C21: =B21*'Unit economics'!C24 -> 36000 | D21: =B21*'Unit economics'!C25 -> 22560
A22: Total | B22: =B20+B21 -> 12 | C22: =C20+C21 -> 148000 | D22: =D20+D21 -> 93416
A23: Gross profit after loan payments | D23: =D22-B16 -> 62816
A25: Year-1 unit targets are draft (owner to confirm). Support-plan revenue is not included.
